{
  "prefs": {
    "destination": "Barcelona",
    "interests": [
      "food",
      "adventure"
    ],
    "budget_level": "luxury",
    "trip_duration": 6
  },
  "data": {
    "narrative": {
      "main_narrative": "\n# Your 6-Day Luxury Adventure in Barcelona\n\nImagine yourself arriving in the vibrant destination of Barcelona, where 6 days of food, adventure experiences await you. This personalized journey combines the best of what Barcelona has to offer for travelers who love food, adventure.\n\n## Trip Highlights\n\nBarcelona offers the perfect blend of experiences for your interests. Each day will bring new discoveries and memories to cherish.\n\n## What Makes This Trip Special\n\nThis itinerary is specially crafted to match your interest in food, adventure while keeping to a luxury budget. You'll get to experience authentic local culture, savor delicious cuisine, and create unforgettable memories.\n\n## Budget Overview\n\n* Accommodations: $350.0 per night\n* Food: $150.0 per day\n* Activities: $200.0 per day\n* Transportation: $140.0 per day\n* Total Estimated Cost: $6552.0 for the entire trip\n\nAre you ready to discover the magic of Barcelona? Let's dive into your day-by-day adventure!\n",
      "daily_plans": [
        {
          "day": 1,
          "content": "\n# Day 1 - Barcelona Adventure\n\n## Morning\n* Start your day with a visit to Barcelona Adventure Park\n* Enjoy breakfast at a local caf\u00e9\n\n## Afternoon\n* Barcelona Hiking Trail\n* Have lunch at a luxury restaurant featuring local cuisine\n\n## Evening\n* Relax and enjoy the Barcelona atmosphere\n* Dinner at a luxury spot known for its food offerings\n"
        },
        {
          "day": 2,
          "content": "\n# Day 2 - Barcelona Adventure\n\n## Morning\n* Start your day with a visit to Barcelona Food Market\n* Enjoy breakfast at a local caf\u00e9\n\n## Afternoon\n* Barcelona Culinary Tour\n* Have lunch at a luxury restaurant featuring local cuisine\n\n## Evening\n* Relax and enjoy the Barcelona atmosphere\n* Dinner at a luxury spot known for its food offerings\n"
        },
        {
          "day": 3,
          "content": "\n# Day 3 - Barcelona Adventure\n\n## Morning\n* Start your day with a visit to Barcelona Outdoor Activities\n* Enjoy breakfast at a local caf\u00e9\n\n## Afternoon\n* Discover more of Barcelona\n* Have lunch at a luxury restaurant featuring local cuisine\n\n## Evening\n* Relax and enjoy the Barcelona atmosphere\n* Dinner at a luxury spot known for its food offerings\n"
        },
        {
          "day": 4,
          "content": "\n# Day 4 - Barcelona Adventure\n\n## Morning\n* Start your day with a visit to Explore Barcelona\n* Enjoy breakfast at a local caf\u00e9\n\n## Afternoon\n* Experience local food scene\n* Have lunch at a luxury restaurant featuring local cuisine\n\n## Evening\n* Relax and enjoy the Barcelona atmosphere\n* Dinner at a luxury spot known for its food offerings\n"
        },
        {
          "day": 5,
          "content": "\n# Day 5 - Barcelona Adventure\n\n## Morning\n* Start your day with a visit to Explore Barcelona\n* Enjoy breakfast at a local caf\u00e9\n\n## Afternoon\n* Experience local food scene\n* Have lunch at a luxury restaurant featuring local cuisine\n\n## Evening\n* Relax and enjoy the Barcelona atmosphere\n* Dinner at a luxury spot known for its food offerings\n"
        },
        {
          "day": 6,
          "content": "\n# Day 6 - Barcelona Adventure\n\n## Morning\n* Start your day with a visit to Traditional Barcelona Restaurant\n* Enjoy breakfast at a local caf\u00e9\n\n## Afternoon\n* Discover more of Barcelona\n* Have lunch at a luxury restaurant featuring local cuisine\n\n## Evening\n* Relax and enjoy the Barcelona atmosphere\n* Dinner at a luxury spot known for its food offerings\n"
        }
      ],
      "budget_narrative": "\n# Budget Breakdown for Your Barcelona Adventure\n\n## Accommodation\n* Luxury level: $350.0 per night\n* Total for 6 nights: $2100.0\n\n## Food\n* Daily budget: $150.0\n* Total for 6 days: $900.0\n\n## Transportation\n* Daily average: $140.0\n* Total: $840.0\n\n## Activities and Attractions\n* Daily budget: $200.0\n* Total: $1200.0\n\n## Total Trip Cost\n* $6552.0 for your 6-day adventure\n\nThis budget is based on luxury level travel in Barcelona, with a focus on food, adventure.\n"
    },
    "budget": {
      "per_day": {
        "accommodation": 350.0,
        "food": 150.0,
        "transportation": 140.0,
        "activities": 200.0,
        "total_daily": 840.0
      },
      "total": {
        "accommodation": 2100.0,
        "food": 900.0,
        "transportation": 840.0,
        "activities": 1200.0,
        "adjustments": 1512.0,
        "grand_total": 6552.0
      },
      "budget_level": "luxury",
      "region_type": "moderate"
    }
  }
}