{
  "prefs": {
    "destination": "Amsterdam",
    "interests": [
      "culture"
    ],
    "budget_level": "budget",
    "trip_duration": 1
  },
  "data": {
    "narrative": {
      "main_narrative": "\n# Your 1-Day Budget Adventure in Amsterdam\n\nImagine yourself arriving in the vibrant destination of Amsterdam, where 1 days of culture experiences await you. This personalized journey combines the best of what Amsterdam has to offer for travelers who love culture.\n\n## Trip Highlights\n\nAmsterdam offers the perfect blend of experiences for your interests. Each day will bring new discoveries and memories to cherish.\n\n## What Makes This Trip Special\n\nThis itinerary is specially crafted to match your interest in culture while keeping to a budget budget. You'll get to experience authentic local culture, savor delicious cuisine, and create unforgettable memories.\n\n## Budget Overview\n\n* Accommodations: $35.0 per night\n* Food: $22.5 per day\n* Activities: $10.0 per day\n* Transportation: $10.0 per day\n* Total Estimated Cost: $81.38 for the entire trip\n\nAre you ready to discover the magic of Amsterdam? Let's dive into your day-by-day adventure!\n",
      "daily_plans": [
        {
          "day": 1,
          "content": "\n# Day 1 - Amsterdam Adventure\n\n## Morning\n* Start your day with a visit to Attend Local Performance in Amsterdam\n* Enjoy breakfast at a local caf\u00e9\n\n## Afternoon\n* Discover more of Amsterdam\n* Have lunch at a budget restaurant featuring local cuisine\n\n## Evening\n* Relax and enjoy the Amsterdam atmosphere\n* Dinner at a budget spot known for its culture offerings\n"
        }
      ],
      "budget_narrative": "\n# Budget Breakdown for Your Amsterdam Adventure\n\n## Accommodation\n* Budget level: $35.0 per night\n* Total for 1 nights: $35.0\n\n## Food\n* Daily budget: $22.5\n* Total for 1 days: $22.5\n\n## Transportation\n* Daily average: $10.0\n* Total: $10.0\n\n## Activities and Attractions\n* Daily budget: $10.0\n* Total: $10.0\n\n## Total Trip Cost\n* $81.38 for your 1-day adventure\n\nThis budget is based on budget level travel in Amsterdam, with a focus on culture.\n"
    },
    "budget": {
      "per_day": {
        "accommodation": 35.0,
        "food": 22.5,
        "transportation": 10.0,
        "activities": 10.0,
        "total_daily": 77.5
      },
      "total": {
        "accommodation": 35.0,
        "food": 22.5,
        "transportation": 10.0,
        "activities": 10.0,
        "adjustments": 3.88,
        "grand_total": 81.38
      },
      "budget_level": "budget",
      "region_type": "moderate"
    }
  }
}